qiyuan/__init__.py
QiYuan-0.dist-info/METADATA
QiYuan-0.dist-info/WHEEL
QiYuan-0.dist-info/top_level.txt
QiYuan-0.dist-info/RECORD
