Metadata-Version: 2.1
Name: QiYuan
Version: 0
Summary: 起源
Classifier: Development Status :: 1 - Planning
